{
    "bounties": [
        {
            "id": "1",
            "title": "Write a X Thread Explaining How Aerodrome's AMM Works on Base",
            "organization": "Aerodrome",
            "rewardAmount": 3000,
            "rewardCurrency": "USDC",
            "deadline": "2025-11-05T23:59:00Z",
            "participants": 3,
            "category": "Content",
            "thumbnailUrl": "/assets/project-1-cover.png"
        },
        {
            "id": "2",
            "title": "Create Meme Content About Brett's Journey on Base",
            "organization": "Brett",
            "rewardAmount": 2000,
            "rewardCurrency": "USDC",
            "deadline": "2025-11-05T23:59:00Z",
            "participants": 5,
            "category": "Content",
            "thumbnailUrl": "/assets/project-2-cover.png"
        },
        {
            "id": "3",
            "title": "Test the Echelon Dashboard on Base, Identify UX Issues",
            "organization": "Echelon",
            "rewardAmount": 20000,
            "rewardCurrency": "USDC",
            "deadline": "2025-11-05T23:59:00Z",
            "participants": 5,
            "category": "Dev",
            "thumbnailUrl": "/assets/project-3-cover.png"
        },
        {
            "id": "4",
            "title": "Create Meme Content About Normie's DeFi Features",
            "organization": "Normie",
            "rewardAmount": 2000,
            "rewardCurrency": "USDC",
            "deadline": "2025-11-05T23:59:00Z",
            "participants": 1,
            "category": "Content",
            "thumbnailUrl": "/assets/project-4-cover.png"
        }
    ]
}
